setup.py
kemosabe/__init__.py
kemosabe/api.py
kemosabe/app.py
kemosabe/configs.py
kemosabe/events.py
kemosabe/exceptions.py
kemosabe/handler.py
kemosabe/helpers.py
kemosabe/mapper.py
kemosabe/payload_builder.py
kemosabe/run.py
kemosabe/wrapper_api.py
kemosabe.egg-info/PKG-INFO
kemosabe.egg-info/SOURCES.txt
kemosabe.egg-info/dependency_links.txt
kemosabe.egg-info/not-zip-safe
kemosabe.egg-info/requires.txt
kemosabe.egg-info/top_level.txt