Metadata-Version: 1.0
Name: kemosabe
Version: 0.8.2
Summary: A Bot Development framework that bot development easy.
Home-page: http://github.com/harowitzblack/kemosabe
Author: Joel Benjamin (Harowitz Black)
Author-email: joelbenjamin093@gmail.com
License: MIT
Platform: UNKNOWN
